{"stats":{"minecraft:custom":{"minecraft:time_since_rest":63912,"minecraft:crouch_one_cm":361,"minecraft:sprint_one_cm":7810,"minecraft:play_time":103659,"minecraft:walk_one_cm":33124,"minecraft:deaths":1,"minecraft:sneak_time":3876,"minecraft:walk_under_water_one_cm":30383,"minecraft:jump":163,"minecraft:damage_dealt":40,"minecraft:leave_game":1,"minecraft:walk_on_water_one_cm":17557,"minecraft:time_since_death":63892,"minecraft:total_world_time":103659,"minecraft:fly_one_cm":717028},"minecraft:picked_up":{"minecraft:ink_sac":1,"minecraft:bamboo":432},"minecraft:used":{"minecraft:netherrack":88,"alexscaves:acid_bucket":7,"securitycraft:reinforced_acacia_pressure_plate":3,"minecraft:lava_bucket":107,"minecraft:magma_block":178,"creeperoverhaul:dripstone_creeper_spawn_egg":11,"minecraft:flint_and_steel":157,"securitycraft:reinforced_blue_stained_glass":89,"minecraft:command_block":1,"create:schematic_table":1,"securitycraft:reinforced_tinted_glass":122,"minecraft:sponge":4,"minecraft:wet_sponge":3,"minecraft:gravel":3,"minecraft:lightning_rod":18}},"DataVersion":3465}